schedulerx/__init__.py
schedulerx/file_manager.py
schedulerx/run_command.py
schedulerx/service.py
schedulerx/timer.py
SchedulerX-1.0.1.dist-info/LICENSE
SchedulerX-1.0.1.dist-info/METADATA
SchedulerX-1.0.1.dist-info/WHEEL
SchedulerX-1.0.1.dist-info/top_level.txt
SchedulerX-1.0.1.dist-info/RECORD
